{
    "l": "Skill User",
    "p": [
        {
            "n": "User",
            "rf": "CreatedById",
            "rl": "Created By ID"
        },
        {
            "n": "User",
            "rf": "LastModifiedById",
            "rl": "Last Modified By ID"
        },
        {
            "n": "ProfileSkill",
            "rf": "ProfileSkillId",
            "rl": "Skill ID"
        },
        {
            "n": "User",
            "rf": "UserId",
            "rl": "User ID"
        }
    ],
    "c": [
        {
            "n": "AttachedContentDocument",
            "rf": "LinkedEntityId",
            "rl": "AttachedContentDocuments"
        },
        {
            "n": "CombinedAttachment",
            "rf": "ParentId",
            "rl": "CombinedAttachments"
        },
        {
            "n": "ContentDocumentLink",
            "rf": "LinkedEntityId",
            "rl": "ContentDocumentLinks"
        },
        {
            "n": "ContentVersion",
            "rf": "FirstPublishLocationId",
            "rl": ""
        },
        {
            "n": "EntitySubscription",
            "rf": "ParentId",
            "rl": "FeedSubscriptionsForEntity"
        },
        {
            "n": "FeedComment",
            "rf": "ParentId",
            "rl": ""
        },
        {
            "n": "FeedItem",
            "rf": "ParentId",
            "rl": ""
        },
        {
            "n": "FeedItem",
            "rf": "RelatedRecordId",
            "rl": ""
        },
        {
            "n": "FlowExecutionErrorEvent",
            "rf": "ContextRecordId",
            "rl": ""
        },
        {
            "n": "FlowRecordRelation",
            "rf": "RelatedRecordId",
            "rl": ""
        },
        {
            "n": "ProcessInstance",
            "rf": "TargetObjectId",
            "rl": "ProcessInstances"
        },
        {
            "n": "ProcessInstanceHistory",
            "rf": "TargetObjectId",
            "rl": "ProcessSteps"
        },
        {
            "n": "ProfileSkillEndorsement",
            "rf": "ProfileSkillUserId",
            "rl": "ProfileSkillUserEndorsements"
        },
        {
            "n": "ProfileSkillUserFeed",
            "rf": "ParentId",
            "rl": "Feeds"
        },
        {
            "n": "ProfileSkillUserHistory",
            "rf": "ProfileSkillUserId",
            "rl": "Histories"
        }
    ],
    "f": [
        {
            "n": "Id",
            "l": "Skill User ID",
            "t": "id"
        },
        {
            "n": "IsDeleted",
            "l": "Deleted",
            "t": "boolean"
        },
        {
            "n": "Name",
            "l": "Skill User Name",
            "t": "string"
        },
        {
            "n": "CreatedDate",
            "l": "Added Date",
            "t": "datetime"
        },
        {
            "n": "CreatedById",
            "l": "Created By ID",
            "t": "reference"
        },
        {
            "n": "LastModifiedDate",
            "l": "Last Modified Date",
            "t": "datetime"
        },
        {
            "n": "LastModifiedById",
            "l": "Last Modified By ID",
            "t": "reference"
        },
        {
            "n": "SystemModstamp",
            "l": "System Modstamp",
            "t": "datetime"
        },
        {
            "n": "ProfileSkillId",
            "l": "Skill ID",
            "t": "reference"
        },
        {
            "n": "UserId",
            "l": "User ID",
            "t": "reference"
        },
        {
            "n": "EndorsementCount",
            "l": "Endorsements",
            "t": "int"
        }
    ]
}