{"l":"Feed Item","p":{"Account":[{"rf":"ParentId","rl":"Parent ID"}],"Asset":[{"rf":"ParentId","rl":"Parent ID"}],"AssetRelationship":[{"rf":"ParentId","rl":"Parent ID"}],"Campaign":[{"rf":"ParentId","rl":"Parent ID"}],"Case":[{"rf":"ParentId","rl":"Parent ID"}],"CollaborationGroup":[{"rf":"ParentId","rl":"Parent ID"}],"Contact":[{"rf":"ParentId","rl":"Parent ID"}],"ContentDocument":[{"rf":"ParentId","rl":"Parent ID"}],"Contract":[{"rf":"ParentId","rl":"Parent ID"}],"Dashboard":[{"rf":"ParentId","rl":"Parent ID"}],"DashboardComponent":[{"rf":"ParentId","rl":"Parent ID"}],"Event":[{"rf":"ParentId","rl":"Parent ID"}],"Lead":[{"rf":"ParentId","rl":"Parent ID"}],"Location":[{"rf":"ParentId","rl":"Parent ID"}],"MyObjectForGIDTest__c":[{"rf":"ParentId","rl":"Parent ID"}],"NadraCustomSetting__c":[{"rf":"ParentId","rl":"Parent ID"}],"OdasevaRoa__RoaRequest__c":[{"rf":"ParentId","rl":"Parent ID"}],"OdasevaRoa__RoaSettings__c":[{"rf":"ParentId","rl":"Parent ID"}],"Opportunity":[{"rf":"ParentId","rl":"Parent ID"}],"Order":[{"rf":"ParentId","rl":"Parent ID"}],"OrderItem":[{"rf":"ParentId","rl":"Parent ID"}],"Payment__c":[{"rf":"ParentId","rl":"Parent ID"}],"Product2":[{"rf":"ParentId","rl":"Parent ID"}],"ProfileSkill":[{"rf":"ParentId","rl":"Parent ID"}],"ProfileSkillEndorsement":[{"rf":"ParentId","rl":"Parent ID"}],"ProfileSkillUser":[{"rf":"ParentId","rl":"Parent ID"},{"rf":"RelatedRecordId","rl":"Related Record ID"}],"Quote":[{"rf":"ParentId","rl":"Parent ID"}],"Relationship_Tester_0__c":[{"rf":"ParentId","rl":"Parent ID"}],"Relationship_Tester_1__c":[{"rf":"ParentId","rl":"Parent ID"}],"Relationship_Tester_2__c":[{"rf":"ParentId","rl":"Parent ID"}],"Relationship_Tester_3__c":[{"rf":"ParentId","rl":"Parent ID"}],"Relationship_Tester_4__c":[{"rf":"ParentId","rl":"Parent ID"}],"Relationship_Tester_5__c":[{"rf":"ParentId","rl":"Parent ID"}],"Report":[{"rf":"ParentId","rl":"Parent ID"}],"Site":[{"rf":"ParentId","rl":"Parent ID"}],"SocialPost":[{"rf":"ParentId","rl":"Parent ID"}],"Solution":[{"rf":"ParentId","rl":"Parent ID"}],"Subscription_Order__c":[{"rf":"ParentId","rl":"Parent ID"}],"Subscription_Product_Feature__c":[{"rf":"ParentId","rl":"Parent ID"}],"Subscription_Product__c":[{"rf":"ParentId","rl":"Parent ID"}],"Subscription__c":[{"rf":"ParentId","rl":"Parent ID"}],"Task":[{"rf":"ParentId","rl":"Parent ID"}],"TestSFTOrgId__c":[{"rf":"ParentId","rl":"Parent ID"}],"Topic":[{"rf":"ParentId","rl":"Parent ID"}],"Update_Data_1__c":[{"rf":"ParentId","rl":"Parent ID"}],"Update_Data_2__c":[{"rf":"ParentId","rl":"Parent ID"}],"Update_Data_3__c":[{"rf":"ParentId","rl":"Parent ID"}],"User":[{"rf":"ParentId","rl":"Parent ID"},{"rf":"CreatedById","rl":"Created By ID"},{"rf":"LastEditById","rl":"Last Edit By ID"},{"rf":"InsertedById","rl":"InsertedBy ID"}],"WorkBadgeDefinition":[{"rf":"ParentId","rl":"Parent ID"}],"WorkOrder":[{"rf":"ParentId","rl":"Parent ID"}],"WorkOrderLineItem":[{"rf":"ParentId","rl":"Parent ID"}],"myObjectForMassDeleteTest__c":[{"rf":"ParentId","rl":"Parent ID"}],"ContentVersion":[{"rf":"RelatedRecordId","rl":"Related Record ID"}],"WorkThanks":[{"rf":"RelatedRecordId","rl":"Related Record ID"}],"FeedComment":[{"rf":"BestCommentId","rl":"Best Comment ID"}]},"c":{"Announcement":[{"rf":"FeedItemId","rl":null}],"FeedAttachment":[{"rf":"FeedEntityId","rl":"FeedAttachments"},{"rf":"RecordId","rl":null}],"FeedComment":[{"rf":"FeedItemId","rl":"FeedComments"}],"FeedLike":[{"rf":"FeedEntityId","rl":null},{"rf":"FeedItemId","rl":"FeedLikes"}],"FeedPollChoice":[{"rf":"FeedItemId","rl":null}],"FeedPollVote":[{"rf":"FeedItemId","rl":null}],"FeedRevision":[{"rf":"FeedEntityId","rl":"FeedRevisions"}],"FeedSignal":[{"rf":"FeedEntityId","rl":null},{"rf":"FeedItemId","rl":"FeedSignals"}],"FeedTrackedChange":[{"rf":"FeedItemId","rl":"FeedTrackedChanges"}],"FlowRecordRelation":[{"rf":"RelatedRecordId","rl":null}],"TopicAssignment":[{"rf":"EntityId","rl":"TopicAssignments"}],"WorkThanks":[{"rf":"FeedItemId","rl":"FeedItemThanks"}]}}