{"l":"Content Document","p":[{"n":"User","rf":"CreatedById","rl":"Created By ID"},{"n":"User","rf":"LastModifiedById","rl":"Last Modified By ID"},{"n":"User","rf":"ArchivedById","rl":"User ID"},{"n":"User","rf":"OwnerId","rl":"Owner ID"},{"n":"ContentVersion","rf":"LatestPublishedVersionId","rl":"Latest Published Version ID"},{"n":"ContentWorkspace","rf":"ParentId","rl":"Parent ID"},{"n":"ContentAsset","rf":"ContentAssetId","rl":"Asset File ID"}],"c":[{"n":"AttachedContentDocument","rf":"ContentDocumentId","rl":""},{"n":"AuthorizationFormText","rf":"ContentDocumentId","rl":"AuthorizationFormTexts"},{"n":"ContentAsset","rf":"ContentDocumentId","rl":""},{"n":"ContentDistribution","rf":"ContentDocumentId","rl":"ContentDistributions"},{"n":"ContentDocumentFeed","rf":"ParentId","rl":"Feeds"},{"n":"ContentDocumentHistory","rf":"ContentDocumentId","rl":"Histories"},{"n":"ContentDocumentLink","rf":"ContentDocumentId","rl":"ContentDocumentLinks"},{"n":"ContentDocumentSubscription","rf":"ContentDocumentId","rl":""},{"n":"ContentFolderMember","rf":"ChildRecordId","rl":""},{"n":"ContentNotification","rf":"EntityIdentifierId","rl":""},{"n":"ContentVersion","rf":"ContentDocumentId","rl":"ContentVersions"},{"n":"ContentVersionComment","rf":"ContentDocumentId","rl":""},{"n":"ContentWorkspaceDoc","rf":"ContentDocumentId","rl":""},{"n":"EntitySubscription","rf":"ParentId","rl":"FeedSubscriptionsForEntity"},{"n":"FeedAttachment","rf":"RecordId","rl":""},{"n":"FeedComment","rf":"ParentId","rl":""},{"n":"FeedItem","rf":"ParentId","rl":""},{"n":"FlowExecutionErrorEvent","rf":"ContextRecordId","rl":""},{"n":"FlowRecordRelation","rf":"RelatedRecordId","rl":""},{"n":"FolderedContentDocument","rf":"ContentDocumentId","rl":""},{"n":"Image","rf":"ContentDocumentId","rl":""},{"n":"OwnedContentDocument","rf":"ContentDocumentId","rl":""},{"n":"TopicAssignment","rf":"EntityId","rl":"TopicAssignments"}],"f":[{"n":"Id","l":"ContentDocument ID","t":"id"},{"n":"CreatedById","l":"Created By ID","t":"reference"},{"n":"CreatedDate","l":"Created","t":"datetime"},{"n":"LastModifiedById","l":"Last Modified By ID","t":"reference"},{"n":"LastModifiedDate","l":"Last Modified Date","t":"datetime"},{"n":"IsArchived","l":"Is Archived","t":"boolean"},{"n":"ArchivedById","l":"User ID","t":"reference"},{"n":"ArchivedDate","l":"Archived Date","t":"date"},{"n":"IsDeleted","l":"Is Deleted","t":"boolean"},{"n":"OwnerId","l":"Owner ID","t":"reference"},{"n":"SystemModstamp","l":"System Modstamp","t":"datetime"},{"n":"Title","l":"Title","t":"string"},{"n":"PublishStatus","l":"Publish Status","t":"picklist"},{"n":"LatestPublishedVersionId","l":"Latest Published Version ID","t":"reference"},{"n":"ParentId","l":"Parent ID","t":"reference"},{"n":"LastViewedDate","l":"Last Viewed Date","t":"datetime"},{"n":"LastReferencedDate","l":"Last Referenced Date","t":"datetime"},{"n":"Description","l":"Description","t":"textarea"},{"n":"ContentSize","l":"Size","t":"int"},{"n":"FileType","l":"File Type","t":"string"},{"n":"FileExtension","l":"File Extension","t":"string"},{"n":"SharingOption","l":"Prevent others from sharing and unsharing","t":"picklist"},{"n":"SharingPrivacy","l":"File Privacy on Records","t":"picklist"},{"n":"ContentModifiedDate","l":"Content Modified Date","t":"datetime"},{"n":"ContentAssetId","l":"Asset File ID","t":"reference"}]}